ArrowTextClassifier/__init__.py
ArrowTextClassifier/classify_text.py
ArrowTextClassifier/main.py
ArrowTextClassifier/model.py
ArrowTextClassifier/summarize_model.py
ArrowTextClassifier/tokenizer.py
ArrowTextClassifier/train.py
ArrowTextClassifier-1.0.3.dist-info/LICENSE
ArrowTextClassifier-1.0.3.dist-info/METADATA
ArrowTextClassifier-1.0.3.dist-info/WHEEL
ArrowTextClassifier-1.0.3.dist-info/top_level.txt
ArrowTextClassifier-1.0.3.dist-info/RECORD
