Metadata-Version: 2.1
Name: ArrowTextClassifier
Version: 1.0.3
Summary: ArrowTextClassifier is a simple text classification tool written in pytorch that allows you to train, summarize, and use text classification models for various tasks.
Home-page: https://github.com/Bhargav230m/ArrowTextClassifier.git
Author: techpowerb
Author-email: technologypower24@gmail.com
Keywords: text classification,natural language processing,NLP,PyTorch,machine learning,deep learning,text summarization,preprocessing,data science,artificial intelligence,dataset,discord
Classifier: Development Status :: 5 - Production/Stable
Classifier: Intended Audience :: Developers
Classifier: License :: OSI Approved :: MIT License
Classifier: Programming Language :: Python :: 3
Classifier: Programming Language :: Python :: 3.6
Classifier: Programming Language :: Python :: 3.7
Classifier: Programming Language :: Python :: 3.8
Classifier: Programming Language :: Python :: 3.9
Classifier: Programming Language :: Python :: 3.10
Classifier: Programming Language :: Python :: 3.11
Classifier: Operating System :: OS Independent
Requires-Python: >=3.6
License-File: LICENSE
Requires-Dist: torch ==2.2.2
Requires-Dist: torchsummary ==1.5.1
Requires-Dist: pandas ==2.2.2
Requires-Dist: scikit-learn ==1.4.2
Requires-Dist: tqdm ==4.66.2
Requires-Dist: numpy ==1.26.4
